app/main.py
app/requirements.txt
app/setup.py
app/rag/api.py
app/rag/cli.py
app/rag/config.py
app/rag/models.py
app/rag/routers.py
app/rag/utilities.py
app/rag/agent/services.py
app/rag/embedding/client.py
app/rag/embedding/services.py
app/rag/llm/client.py
app/rag/llm/services.py
app/rag/llm/utilities.py
app/rag/test/client.py
app/rag/train/client.py
app/rag/v1/routers.py
app/rag/v1/services.py
app/rag/vector_store/client.py
app/rag/vector_store/services.py
pirag-0.2.2.dist-info/licenses/LICENSE
pirag-0.2.2.dist-info/METADATA
pirag-0.2.2.dist-info/WHEEL
pirag-0.2.2.dist-info/entry_points.txt
pirag-0.2.2.dist-info/top_level.txt
pirag-0.2.2.dist-info/RECORD
