Metadata-Version: 2.4
Name: pirag
Version: 0.2.2
Summary: CLI Projects of On-Premise RAG. You can use your own LLM and vector DB. Or just add remote LLM servers and vector DB.
Author-email: semir4in <semir4in@gmail.com>, jyje <jyjeon@outlook.com>
Project-URL: Homepage, https://github.com/jyje/pilot-onpremise-rag
Project-URL: Repository, https://github.com/jyje/pilot-onpremise-rag
Project-URL: Issue, https://github.com/jyje/pilot-onpremise-rag/issues
Requires-Python: >=3.9
License-File: LICENSE
Requires-Dist: dynaconf<3.3
Requires-Dist: loguru<0.8
Requires-Dist: pytest<8.4
Requires-Dist: fastapi<0.116
Requires-Dist: uvicorn<0.35
Requires-Dist: ragas<0.3
Requires-Dist: pymilvus<2.6
Requires-Dist: langchain-openai<0.4
Requires-Dist: langchain-ollama<0.4
Dynamic: license-file
